interactions/ext/message_commands/__init__.py
interactions/ext/message_commands/_setup.py
interactions/ext/message_commands/cog.py
interactions/ext/message_commands/context.py
interactions/ext/message_commands/decor.py
interactions/ext/message_commands/errors.py
interactions/ext/message_commands/message_commands.py
interactions/ext/message_commands/prefixes.py
interactions_message_commands-0.1.1.dist-info/LICENSE
interactions_message_commands-0.1.1.dist-info/METADATA
interactions_message_commands-0.1.1.dist-info/WHEEL
interactions_message_commands-0.1.1.dist-info/top_level.txt
interactions_message_commands-0.1.1.dist-info/RECORD
