Metadata-Version: 2.1
Name: interactions-message-commands
Version: 0.1.1
Summary: Message commands extension for discord-py-interactions
Home-page: https://github.com/Toricane/interactions-message-commands
Author: Toricane
Author-email: prjwl028@gmail.com
License: MIT
Platform: UNKNOWN
Classifier: Programming Language :: Python :: 3
Classifier: Development Status :: 4 - Beta
Classifier: License :: OSI Approved :: MIT License
Classifier: Operating System :: OS Independent
License-File: LICENSE
Requires-Dist: discord-py-interactions (>=4.0.1)
